[{"line":1,"elements":[{"start_timestamp":"2022-11-15T21:57:53.913Z","line":36,"name":"Login with a wrong email","description":"","id":"sconto-login;login-with-a-wrong-email","type":"scenario","keyword":"Scenario","steps":[{"result":{"duration":7586929800,"status":"passed"},"line":37,"name":"Navigate to Home page","match":{"location":"com.telran.sconto.steps.HomePageSteps.<init>(HomePageSteps.java:15)"},"keyword":"Given "},{"result":{"duration":1412723100,"status":"passed"},"line":38,"name":"Click on Anmelden icon","match":{"location":"com.telran.sconto.steps.HomePageSteps.<init>(HomePageSteps.java:21)"},"keyword":"When "},{"result":{"duration":113683100,"status":"passed"},"line":39,"name":"Login Page displayed","match":{"location":"com.telran.sconto.steps.LoginPageSteps.<init>(LoginPageSteps.java:19)"},"keyword":"Then "},{"result":{"duration":330835000,"status":"passed"},"line":41,"name":"Enter the valid email and empty password","match":{"location":"com.telran.sconto.steps.LoginPageSteps.<init>(LoginPageSteps.java:46)"},"keyword":"When "},{"result":{"duration":146114400,"status":"passed"},"line":42,"name":"Click Anmelden button","match":{"location":"com.telran.sconto.steps.LoginPageSteps.<init>(LoginPageSteps.java:29)"},"keyword":"And "},{"result":{"duration":55964000,"status":"passed"},"line":43,"name":"Demands for valid password message appeared","match":{"location":"com.telran.sconto.steps.LoginPageSteps.<init>(LoginPageSteps.java:50)"},"keyword":"Then "}],"tags":[{"name":"@emptyPassword"}]}],"name":"Sconto Login","description":"  log in the website to seethe users Area","id":"sconto-login","keyword":"Feature","uri":"file:src/test/resources/features/login.feature","tags":[]}]